{
  "aor": 0.0029787121212121216,
  "aqi": 0.016969787045454543,
  "bids_meta": {
    "EchoTime": 0.037,
    "EffectiveEchoSpacing": 0.0005800087233,
    "FlipAngle": 52,
    "PhaseEncodingDirection": "j-",
    "RepetitionTime": 2.47,
    "SliceTiming": [
      0,
      0.4175,
      0.08499999999,
      0.5,
      0.1675,
      0.585,
      0.25,
      0.6675,
      0.335,
      0,
      0.4175,
      0.08499999999,
      0.5,
      0.1675,
      0.585,
      0.25,
      0.6675,
      0.335,
      0,
      0.4175,
      0.08499999999,
      0.5,
      0.1675,
      0.585,
      0.25,
      0.6675,
      0.335,
      0,
      0.4175,
      0.08499999999,
      0.5,
      0.1675,
      0.585,
      0.25,
      0.6675,
      0.335,
      0,
      0.4175,
      0.08499999999,
      0.5,
      0.1675,
      0.585,
      0.25,
      0.6675,
      0.335,
      0,
      0.4175,
      0.08499999999,
      0.5,
      0.1675,
      0.585,
      0.25,
      0.6675,
      0.335,
      0,
      0.4175,
      0.08499999999,
      0.5,
      0.1675,
      0.585,
      0.25,
      0.6675,
      0.335,
      0,
      0.4175,
      0.08499999999,
      0.5,
      0.1675,
      0.585,
      0.25,
      0.6675,
      0.335
    ],
    "TaskName": "SESS05",
    "dataset": "ds003717",
    "modality": "bold",
    "subject_id": "15",
    "task_id": "SESS05"
  },
  "dummy_trs": 3,
  "dvars_nstd": 57.32241789229011,
  "dvars_std": 1.0501768105343507,
  "dvars_vstd": 0.9958019310687025,
  "efc": 0.5705056295204283,
  "fber": 275.9906311035156,
  "fd_mean": 0.18747688131788298,
  "fd_num": 40,
  "fd_perc": 30.303030303030305,
  "fwhm_avg": 2.6067217674770014,
  "fwhm_x": 2.326250138655313,
  "fwhm_y": 2.746215,
  "fwhm_z": 2.747700163775692,
  "gcor": 0.00462818,
  "gsr_x": 0.009811142459511757,
  "gsr_y": 0.05702775716781616,
  "provenance": {
    "md5sum": "7643cc0d5cf3590b7317b38516f9cd81",
    "settings": {
      "fd_thres": 0.2,
      "testing": false
    },
    "software": "mriqc",
    "version": "23.0.0",
    "webapi_port": null,
    "webapi_url": "https://mriqc.nimh.nih.gov/api/v1"
  },
  "size_t": 132,
  "size_x": 104,
  "size_y": 104,
  "size_z": 72,
  "snr": 2.2813002193381298,
  "spacing_tr": 2.4700000286102295,
  "spacing_x": 1.9999998807907104,
  "spacing_y": 2.0,
  "spacing_z": 1.9999998807907104,
  "summary_bg_k": 85.53877398689401,
  "summary_bg_mad": 149.79917725092457,
  "summary_bg_mean": 439.0619812011719,
  "summary_bg_median": 236.67225646972656,
  "summary_bg_n": 490499.0,
  "summary_bg_p05": 109.25223388671876,
  "summary_bg_p95": 1503.7491455078125,
  "summary_bg_stdv": 628.5740356445312,
  "summary_fg_k": 1.3634784889039127,
  "summary_fg_mad": 1531.883901770191,
  "summary_fg_mean": 4315.52587890625,
  "summary_fg_median": 4025.858154296875,
  "summary_fg_n": 178327.0,
  "summary_fg_p05": 2000.1008544921874,
  "summary_fg_p95": 7596.196533203121,
  "summary_fg_stdv": 1764.7159423828125,
  "tsnr": 21.104442596435547
}