{
  "aor": 0.0006966666666666666,
  "aqi": 0.0070033427407407405,
  "bids_meta": {
    "EchoTime": 0.037,
    "EffectiveEchoSpacing": 0.0005800087233,
    "FlipAngle": 52,
    "PhaseEncodingDirection": "j-",
    "RepetitionTime": 2.47,
    "SliceTiming": [
      0,
      0.4175,
      0.08500000002,
      0.5,
      0.1675,
      0.585,
      0.25,
      0.6675,
      0.335,
      0,
      0.4175,
      0.08500000002,
      0.5,
      0.1675,
      0.585,
      0.25,
      0.6675,
      0.335,
      0,
      0.4175,
      0.08500000002,
      0.5,
      0.1675,
      0.585,
      0.25,
      0.6675,
      0.335,
      0,
      0.4175,
      0.08500000002,
      0.5,
      0.1675,
      0.585,
      0.25,
      0.6675,
      0.335,
      0,
      0.4175,
      0.08500000002,
      0.5,
      0.1675,
      0.585,
      0.25,
      0.6675,
      0.335,
      0,
      0.4175,
      0.08500000002,
      0.5,
      0.1675,
      0.585,
      0.25,
      0.6675,
      0.335,
      0,
      0.4175,
      0.08500000002,
      0.5,
      0.1675,
      0.585,
      0.25,
      0.6675,
      0.335,
      0,
      0.4175,
      0.08500000002,
      0.5,
      0.1675,
      0.585,
      0.25,
      0.6675,
      0.335
    ],
    "TaskName": "SESS01",
    "dataset": "ds003717",
    "modality": "bold",
    "subject_id": "40",
    "task_id": "SESS01"
  },
  "dummy_trs": 0,
  "dvars_nstd": 39.042838623432836,
  "dvars_std": 1.0377065626119397,
  "dvars_vstd": 1.0002707667164186,
  "efc": 0.5065626033883673,
  "fber": 735.5908813476562,
  "fd_mean": 0.07472397382375054,
  "fd_num": 3,
  "fd_perc": 2.2222222222222223,
  "fwhm_avg": 2.57597,
  "fwhm_x": 2.470355,
  "fwhm_y": 2.776715,
  "fwhm_z": 2.48084,
  "gcor": 0.00712457,
  "gsr_x": -0.024173256009817123,
  "gsr_y": 0.06961369514465332,
  "provenance": {
    "md5sum": "b86794dfd0eb0d48f9a289f06e058c1b",
    "settings": {
      "fd_thres": 0.2,
      "testing": false
    },
    "software": "mriqc",
    "version": "23.0.0",
    "webapi_port": null,
    "webapi_url": "https://mriqc.nimh.nih.gov/api/v1"
  },
  "size_t": 135,
  "size_x": 104,
  "size_y": 104,
  "size_z": 72,
  "snr": 2.9634948651264694,
  "spacing_tr": 2.4700000286102295,
  "spacing_x": 2.0,
  "spacing_y": 2.0,
  "spacing_z": 2.0,
  "summary_bg_k": 89.10973459765954,
  "summary_bg_mad": 93.70845281459246,
  "summary_bg_mean": 357.4168701171875,
  "summary_bg_median": 173.17294311523438,
  "summary_bg_n": 549867.0,
  "summary_bg_p05": 105.5787467956543,
  "summary_bg_p95": 1300.3821411132797,
  "summary_bg_stdv": 575.9505615234375,
  "summary_fg_k": 0.9232675387552058,
  "summary_fg_mad": 1489.9354166613184,
  "summary_fg_mean": 5015.58544921875,
  "summary_fg_median": 4774.4521484375,
  "summary_fg_n": 134596.0,
  "summary_fg_p05": 2855.6658935546875,
  "summary_fg_p95": 7991.2884521484375,
  "summary_fg_stdv": 1611.0823974609375,
  "tsnr": 35.64964294433594
}