{
  "aor": 0.001381203007518797,
  "aqi": 0.013438542255639096,
  "bids_meta": {
    "EchoTime": 0.037,
    "EffectiveEchoSpacing": 0.0005800087233,
    "FlipAngle": 52,
    "PhaseEncodingDirection": "j-",
    "RepetitionTime": 2.47,
    "SliceTiming": [
      0,
      0.4175,
      0.08500000002,
      0.5,
      0.1675,
      0.585,
      0.25,
      0.6675,
      0.335,
      0,
      0.4175,
      0.08500000002,
      0.5,
      0.1675,
      0.585,
      0.25,
      0.6675,
      0.335,
      0,
      0.4175,
      0.08500000002,
      0.5,
      0.1675,
      0.585,
      0.25,
      0.6675,
      0.335,
      0,
      0.4175,
      0.08500000002,
      0.5,
      0.1675,
      0.585,
      0.25,
      0.6675,
      0.335,
      0,
      0.4175,
      0.08500000002,
      0.5,
      0.1675,
      0.585,
      0.25,
      0.6675,
      0.335,
      0,
      0.4175,
      0.08500000002,
      0.5,
      0.1675,
      0.585,
      0.25,
      0.6675,
      0.335,
      0,
      0.4175,
      0.08500000002,
      0.5,
      0.1675,
      0.585,
      0.25,
      0.6675,
      0.335,
      0,
      0.4175,
      0.08500000002,
      0.5,
      0.1675,
      0.585,
      0.25,
      0.6675,
      0.335
    ],
    "TaskName": "SESS02",
    "dataset": "ds003717",
    "modality": "bold",
    "subject_id": "43",
    "task_id": "SESS02"
  },
  "dummy_trs": 2,
  "dvars_nstd": 49.23857787136364,
  "dvars_std": 1.0617904075,
  "dvars_vstd": 0.973140404621212,
  "efc": 0.5948963797864447,
  "fber": 307.1955261230469,
  "fd_mean": 0.10027110248526205,
  "fd_num": 2,
  "fd_perc": 1.5037593984962405,
  "fwhm_avg": 2.853365,
  "fwhm_x": 2.6739,
  "fwhm_y": 3.010035,
  "fwhm_z": 2.87616,
  "gcor": 0.00307914,
  "gsr_x": -0.030879568308591843,
  "gsr_y": 0.09424450993537903,
  "provenance": {
    "md5sum": "6bf09d807705ce285b79236c73f70dfb",
    "settings": {
      "fd_thres": 0.2,
      "testing": false
    },
    "software": "mriqc",
    "version": "23.0.0",
    "webapi_port": null,
    "webapi_url": "https://mriqc.nimh.nih.gov/api/v1"
  },
  "size_t": 133,
  "size_x": 104,
  "size_y": 104,
  "size_z": 72,
  "snr": 2.0973559774127106,
  "spacing_tr": 2.4700000286102295,
  "spacing_x": 2.0,
  "spacing_y": 2.0,
  "spacing_z": 2.0,
  "summary_bg_k": 28.89379257269057,
  "summary_bg_mad": 165.89340618902023,
  "summary_bg_mean": 596.7722778320312,
  "summary_bg_median": 255.43862915039062,
  "summary_bg_n": 451711.0,
  "summary_bg_p05": 118.36138534545898,
  "summary_bg_p95": 2383.8057861328125,
  "summary_bg_stdv": 1003.5567626953125,
  "summary_fg_k": 1.3103740109577657,
  "summary_fg_mad": 1976.9476227258929,
  "summary_fg_mean": 5138.69091796875,
  "summary_fg_median": 4719.7724609375,
  "summary_fg_n": 208864.0,
  "summary_fg_p05": 2330.0635864257815,
  "summary_fg_p95": 9518.458593749998,
  "summary_fg_stdv": 2250.338623046875,
  "tsnr": 26.782901763916016
}